topas_tools/__init__.py
topas_tools/blender_mini.py
topas_tools/cif2patterson.py
topas_tools/cif2topas.py
topas_tools/expandcell.py
topas_tools/fh2topas.py
topas_tools/make_superflip.py
topas_tools/restraints_statistics.py
topas_tools/stripcif.py
topas_tools/topas_ndxan.py
topas_tools/topas_restraints.py
topas_tools/topasdiff.py
topas_tools/topasdiff_gui.py
topas_tools-1.1.0.dist-info/licenses/LICENCE
topas_tools-1.1.0.dist-info/METADATA
topas_tools-1.1.0.dist-info/WHEEL
topas_tools-1.1.0.dist-info/entry_points.txt
topas_tools-1.1.0.dist-info/top_level.txt
topas_tools-1.1.0.dist-info/RECORD
