Metadata-Version: 2.4
Name: topas_tools
Version: 1.1.0
Summary: Python scripts to help structure refinement with TOPAS
Author-email: Stef Smeets <stef.smeets@gmail.com>
License: MIT License
Project-URL: homepage, https://github.com/stefsmeets/topas_tools
Project-URL: issues, https://github.com/stefsmeets/topas_tools/issues
Project-URL: changelog, https://github.com/steftmeest/topas_tools/releases
Keywords: powder-diffraction,profile-refinement,structure-refinement,topas
Classifier: Development Status :: 5 - Production/Stable
Classifier: Intended Audience :: Science/Research
Classifier: License :: OSI Approved :: MIT License
Classifier: Natural Language :: English
Classifier: Operating System :: OS Independent
Classifier: Programming Language :: Python :: 3
Classifier: Programming Language :: Python :: 3.10
Classifier: Programming Language :: Python :: 3.11
Classifier: Programming Language :: Python :: 3.12
Classifier: Programming Language :: Python :: 3.13
Classifier: Topic :: Scientific/Engineering
Requires-Python: >=3.9
License-File: LICENCE
Requires-Dist: matplotlib
Requires-Dist: numpy
Requires-Dist: pandas
Requires-Dist: scipy
Provides-Extra: develop
Requires-Dist: bump-my-version; extra == "develop"
Requires-Dist: pre-commit; extra == "develop"
Provides-Extra: publishing
Requires-Dist: twine; extra == "publishing"
Requires-Dist: wheel; extra == "publishing"
Requires-Dist: build; extra == "publishing"
Dynamic: license-file
